Metadata-Version: 1.0
Name: dvalidator
Version: 0.1.4
Summary: dvalidator validation attributes
Home-page: https://github.com/kakabara/dvalidator
Author: Vlasov Sergei
Author-email: kakabara@outlook.com
License: MIT
Platform: UNKNOWN
